LICENSE
MANIFEST.in
README.rst
publicize.py
setup.cfg
setup.py
publicize.egg-info/PKG-INFO
publicize.egg-info/SOURCES.txt
publicize.egg-info/dependency_links.txt
publicize.egg-info/top_level.txt