Metadata-Version: 1.1
Name: publicize
Version: 1.5.0
Summary: Utilities to manage the way a module is exported
Home-page: http://pypi.python.org/pypi/publicize/
Author: Dan Snider
Author-email: dan.snider.cu@outlook.com
License: MIT
Platform: UNKNOWN
Classifier: Programming Language :: Python :: 3
Classifier: Programming Language :: Python :: 2
Classifier: Intended Audience :: Developers
Classifier: License :: OSI Approved :: MIT License
Classifier: Topic :: Software Development :: Libraries
Classifier: Topic :: Utilities
